ondewo/__init__.py
ondewo/nlu/__init__.py
ondewo/nlu/agent_pb2.py
ondewo/nlu/agent_pb2.pyi
ondewo/nlu/agent_pb2_grpc.py
ondewo/nlu/aiservices_pb2.py
ondewo/nlu/aiservices_pb2.pyi
ondewo/nlu/aiservices_pb2_grpc.py
ondewo/nlu/async_client.py
ondewo/nlu/ccai_project_pb2.py
ondewo/nlu/ccai_project_pb2.pyi
ondewo/nlu/ccai_project_pb2_grpc.py
ondewo/nlu/client.py
ondewo/nlu/client_config.py
ondewo/nlu/client_pool.py
ondewo/nlu/common_pb2.py
ondewo/nlu/common_pb2.pyi
ondewo/nlu/common_pb2_grpc.py
ondewo/nlu/context_pb2.py
ondewo/nlu/context_pb2.pyi
ondewo/nlu/context_pb2_grpc.py
ondewo/nlu/entity_type_pb2.py
ondewo/nlu/entity_type_pb2.pyi
ondewo/nlu/entity_type_pb2_grpc.py
ondewo/nlu/intent_pb2.py
ondewo/nlu/intent_pb2.pyi
ondewo/nlu/intent_pb2_grpc.py
ondewo/nlu/operation_metadata_pb2.py
ondewo/nlu/operation_metadata_pb2.pyi
ondewo/nlu/operation_metadata_pb2_grpc.py
ondewo/nlu/operations_pb2.py
ondewo/nlu/operations_pb2.pyi
ondewo/nlu/operations_pb2_grpc.py
ondewo/nlu/project_role_pb2.py
ondewo/nlu/project_role_pb2.pyi
ondewo/nlu/project_role_pb2_grpc.py
ondewo/nlu/project_statistics_pb2.py
ondewo/nlu/project_statistics_pb2.pyi
ondewo/nlu/project_statistics_pb2_grpc.py
ondewo/nlu/py.typed
ondewo/nlu/server_statistics_pb2.py
ondewo/nlu/server_statistics_pb2.pyi
ondewo/nlu/server_statistics_pb2_grpc.py
ondewo/nlu/session_pb2.py
ondewo/nlu/session_pb2.pyi
ondewo/nlu/session_pb2_grpc.py
ondewo/nlu/user_pb2.py
ondewo/nlu/user_pb2.pyi
ondewo/nlu/user_pb2_grpc.py
ondewo/nlu/utility_pb2.py
ondewo/nlu/utility_pb2.pyi
ondewo/nlu/utility_pb2_grpc.py
ondewo/nlu/webhook_pb2.py
ondewo/nlu/webhook_pb2.pyi
ondewo/nlu/webhook_pb2_grpc.py
ondewo/nlu/convenience/__init__.py
ondewo/nlu/convenience/shared_request_data.py
ondewo/nlu/core/__init__.py
ondewo/nlu/core/async_services_container.py
ondewo/nlu/core/async_services_interface.py
ondewo/nlu/core/services_container.py
ondewo/nlu/core/services_interface.py
ondewo/nlu/scripts/__init__.py
ondewo/nlu/scripts/client_example_script.py
ondewo_nlu_client-6.2.0.dist-info/LICENSE
ondewo_nlu_client-6.2.0.dist-info/METADATA
ondewo_nlu_client-6.2.0.dist-info/WHEEL
ondewo_nlu_client-6.2.0.dist-info/top_level.txt
ondewo_nlu_client-6.2.0.dist-info/RECORD
