Metadata-Version: 2.1
Name: ondewo-nlu-client
Version: 6.2.0
Summary: ONDEWO Natural Language Understanding (NLU) Client library for Python
Home-page: https://github.com/ondewo/ondewo-nlu-client-python
Author: ONDEWO GmbH
Author-email: office@ondewo.com
Classifier: Development Status :: 5 - Production/Stable
Classifier: Intended Audience :: Developers
Classifier: License :: OSI Approved :: Apache Software License
Classifier: Operating System :: OS Independent
Classifier: Programming Language :: Python :: 3.9
Classifier: Programming Language :: Python :: 3.10
Classifier: Programming Language :: Python :: 3.11
Classifier: Programming Language :: Python :: 3.12
Classifier: Topic :: Software Development :: Libraries
Requires-Python: >=3
License-File: LICENSE
Requires-Dist: dataclasses-json
Requires-Dist: google-api-core
Requires-Dist: grpcio
Requires-Dist: grpcio-reflection
Requires-Dist: grpcio-tools
Requires-Dist: ondewo-client-utils>=3.1.0
Requires-Dist: ondewo-logging
Requires-Dist: polling
Requires-Dist: protobuf
Requires-Dist: python-dateutil
Requires-Dist: regex
Requires-Dist: setuptools
